xiaobaiinstaller/__init__.py
xiaobaiinstaller/installer.py
xiaobaiinstaller/logo.ico
xiaobaiinstaller/xiaobaicore.cp38-win_amd64.pyd
xiaobaiinstaller-2.5.dist-info/LICENSE
xiaobaiinstaller-2.5.dist-info/METADATA
xiaobaiinstaller-2.5.dist-info/WHEEL
xiaobaiinstaller-2.5.dist-info/entry_points.txt
xiaobaiinstaller-2.5.dist-info/top_level.txt
xiaobaiinstaller-2.5.dist-info/RECORD
