Metadata-Version: 2.1
Name: xiaobaiinstaller
Version: 2.5
Summary: Xiaobai Test Tools Install
Home-page: https://gitee.com/big_touch/xiaobaiinstaller
Author: Tser
Author-email: 807447312@qq.com
License: UNKNOWN
Keywords: xiaobai tool test install
Platform: UNKNOWN
Classifier: Programming Language :: Python :: 3
Classifier: Programming Language :: Python :: 3.7
Classifier: Programming Language :: Python :: 3.8
Classifier: License :: OSI Approved :: Apache Software License
Classifier: Operating System :: OS Independent
Requires-Python: >=3.4
Requires-Dist: requests-html
